{
  "name": "CHOROIDAL OSTEOMA",
  "slug": "choroidal_osteoma",
  "chapter": "ORBITAL AND OCULAR DISORDERS",
  "source_file": "processed_clusters/disease_entries/orbital_and_ocular_disorders/choroidal_osteoma.md",
  "definition": "rare juxtapapillary tumor of mature bone",
  "demographics": {
    "Age": "young woman",
    "Location": "may be bilateral"
  },
  "dominant_finding": "small flat very dense curvilinear mass aligned with choroidal margin of globe",
  "distribution": "may be bilateral",
  "discriminating_features": [
    "small flat very dense curvilinear mass aligned with choroidal margin of globe"
  ],
  "other_features": {
    "general": [
      "small flat very dense curvilinear mass aligned with choroidal margin of globe"
    ]
  },
  "clinical": {}
}