{
  "name": "GANGLION CELL TUMOR",
  "slug": "ganglion_cell_tumor",
  "chapter": "CENTRAL NEUROCYTOMA",
  "source_file": "processed_clusters/disease_entries/central_neurocytoma/ganglion_cell_tumor.md",
  "definition": "rare benign tumor composed of mature ganglion cells LHERMITTE-DUCLOS DISEASE rare hamartomatous disorder uncommon slow-growing relatively benign tumor composed of glial + nerve cells DESMOPLASTIC INFANTILE ASTROCYTOMA = SUPERFICIAL CEREBRAL uncommon variety of ganglioglioma exclusively in infants",
  "demographics": {
    "Prevalence": "0.1-0.5% of all brain tumors",
    "Age": "children + young adults",
    "Associated with": "dysplastic + malformed brain",
    "Histo": "purely neuronal tumor composed of abnormal mature ganglion cells without",
    "Location": "floor of 3rd ventricle > temporal lobe > cerebellum > parietooccipital region >",
    "Path": "disruption of normal cerebellar laminar structure",
    "Peak age": "10-20 years; in 80% < 30 years of age; M > F"
  },
  "dominant_finding": "hydrocephalus ← compression of 4th ventricle + effacement of cerebellopontine angle",
  "distribution": "floor of 3rd ventricle > temporal lobe > cerebellum > parietooccipital region >",
  "discriminating_features": [
    "variable (hypo- / isointense) nonspecific MR appearance on T1WI",
    "CHARACTERISTIC extension of enhancement to leptomeningeal margin ← firm dural",
    "hyperattenuating mass with little mass effect",
    "hypo- / isoattenuating cerebellar mass",
    "hydrocephalus ← compression of 4th ventricle + effacement of cerebellopontine angle"
  ],
  "other_features": {
    "general": [],
    "CT": [
      "hyperattenuating mass with little mass effect",
      "hypo- / isoattenuating cerebellar mass",
      "hydrocephalus ← compression of 4th ventricle + effacement of cerebellopontine angle",
      "calcification uncommon",
      "NO enhancement",
      "hypoattenuating (38%) / mixed attenuation (32%) / isoattenuating (15%) /",
      "± remodeling of skull",
      "contrast enhancement (16-80%)"
    ],
    "MR": [
      "iso- to hypointense on T1WI + T2WI",
      "bright on proton density images",
      "cerebellar mass with \"striated cerebellum\" sign = tiger-striped / corduroy laminated",
      "hyper- and isointense relative to gray matter on T2WI",
      "iso- and hypointense relative to gray matter on T1WI",
      "enhancement extremely uncommon",
      "± syringohydromyelia",
      "circumscribed slow-growing mass:",
      "solid (43%) / purely cystic (5%) / solid-cystic combination (52%)",
      "calcifications (30%)",
      "little associated mass effect / vasogenic edema",
      "variable (hypo- / isointense) nonspecific MR appearance on T1WI",
      "commonly at least one hyperintense region on T2WI",
      "cystic component may have higher signal intensity than CSF ← gelatinous material",
      "nonenhancing / ringlike / homogeneously intense enhancement",
      "exceptionally large heterogeneously mass:",
      "slightly hyperattenuating solid portion typically located along cortical margin",
      "cystic components",
      "intense enhancement of solid component",
      "CHARACTERISTIC extension of enhancement to leptomeningeal margin ← firm dural",
      "rare vasogenic edema",
      "NO calcification"
    ],
    "XRAY": [
      "thinning of skull in occipital region"
    ]
  },
  "clinical": {
    "Rx": "decompression of ventricles + resection of mass",
    "Prognosis": "favorable; malignant degeneration (6%)"
  }
}