{
  "finding": "C. TRAUMA",
  "slug": "c_trauma_4f9ec3",
  "chapter": "F. TRAUMA",
  "source_file": "processed_clusters/f_trauma/c_trauma_4f9ec3.md",
  "quality_score": 0.467,
  "cluster_type": "differential",
  "differentials": [
    {
      "name": "Pulmonary hematoma",
      "raw": "Pulmonary hematoma",
      "frequency": null
    },
    {
      "name": "THROMBOEMBOLISM",
      "raw": "THROMBOEMBOLISM",
      "frequency": null
    },
    {
      "name": "Sarcoidosis, alveolar type",
      "raw": "Sarcoidosis, alveolar type",
      "frequency": null
    },
    {
      "name": "Septic emboli",
      "raw": "Septic emboli",
      "frequency": null
    },
    {
      "name": "Metastasis",
      "raw": "Metastasis",
      "frequency": null
    },
    {
      "name": "Lymphoma, Lung primary, Lymphomatoid granulomatosis",
      "raw": "Lymphoma, Lung primary, Lymphomatoid granulomatosis",
      "frequency": null
    },
    {
      "name": "Alveolar cell carcinoma",
      "raw": "Alveolar cell carcinoma",
      "frequency": null
    },
    {
      "name": "Rheumatoid lung",
      "raw": "Rheumatoid lung",
      "frequency": null
    },
    {
      "name": "Wegener granulomatosis",
      "raw": "Wegener granulomatosis",
      "frequency": null
    },
    {
      "name": "Fungus",
      "raw": "Fungus",
      "frequency": null
    },
    {
      "name": "Tuberculosis",
      "raw": "Tuberculosis",
      "frequency": null
    }
  ],
  "criteria": {},
  "context": "Shaggy Pulmonary Nodule mnemonic:   Shaggy Sue Made Loving A Really Wild Fantasy Today"
}