{
  "finding": "F. OTHERS",
  "slug": "f_others",
  "chapter": "E. EXTRINSIC COMPRESSION",
  "source_file": "processed_clusters/e_extrinsic_compression/f_others.md",
  "quality_score": 0.5,
  "cluster_type": "differential",
  "differentials": [
    {
      "name": "Superior mesenteric artery syndrome: extensive burns, body cast, rapid weight loss, prolonged bed rest",
      "raw": "Superior mesenteric artery syndrome: extensive burns, body cast, rapid weight loss, prolonged bed rest",
      "frequency": null
    },
    {
      "name": "Bezoar (in gastrectomized patient) mnemonic:   VA BADD TU BADD child adult",
      "raw": "Bezoar (in gastrectomized patient) mnemonic:   VA BADD TU BADD child adult",
      "frequency": null
    },
    {
      "name": "Volvulus",
      "raw": "Volvulus",
      "frequency": null
    },
    {
      "name": "Tumor",
      "raw": "Tumor",
      "frequency": null
    },
    {
      "name": "Atresia",
      "raw": "Atresia",
      "frequency": null
    },
    {
      "name": "Ulcer",
      "raw": "Ulcer",
      "frequency": null
    },
    {
      "name": "Bands",
      "raw": "Bands",
      "frequency": null
    },
    {
      "name": "Bands",
      "raw": "Bands",
      "frequency": null
    },
    {
      "name": "Annular pancreas",
      "raw": "Annular pancreas",
      "frequency": null
    },
    {
      "name": "Annular pancreas",
      "raw": "Annular pancreas",
      "frequency": null
    },
    {
      "name": "Duplication",
      "raw": "Duplication",
      "frequency": null
    },
    {
      "name": "Duplication",
      "raw": "Duplication",
      "frequency": null
    },
    {
      "name": "Diverticulum",
      "raw": "Diverticulum",
      "frequency": null
    },
    {
      "name": "Diverticulum",
      "raw": "Diverticulum",
      "frequency": null
    }
  ],
  "criteria": {},
  "context": "Abdominal plain film: √  \"double-bubble\" sign = air-fluid levels in stomach + duodenum √  frequently normal ← absence of gas from vomiting Jejunal and Ileal Obstruction =  SMALL BOWEL OBSTRUCTION (SBO) Frequency:   accounts for 20% of all surgical admissions Mortality:  5.5% due to strangulation (paradigm: \"Never let the sun rise or set on an obstructed small bowel\") Cause:"
}